mitmproxy_httpolice.py
mitmproxy_HTTPolice-0.9.0.dist-info/LICENSE.txt
mitmproxy_HTTPolice-0.9.0.dist-info/METADATA
mitmproxy_HTTPolice-0.9.0.dist-info/WHEEL
mitmproxy_HTTPolice-0.9.0.dist-info/top_level.txt
mitmproxy_HTTPolice-0.9.0.dist-info/RECORD
