Metadata-Version: 2.1
Name: mitmproxy-HTTPolice
Version: 0.9.0
Summary: mitmproxy integration for HTTPolice
Home-page: https://github.com/vfaronov/mitmproxy-httpolice
Author: Vasiliy Faronov
Author-email: vfaronov@gmail.com
License: MIT
Keywords: HTTP message request response standards RFC validator proxy
Platform: UNKNOWN
Classifier: Intended Audience :: Developers
Classifier: License :: OSI Approved :: MIT License
Classifier: Programming Language :: Python :: 3
Classifier: Programming Language :: Python :: 3 :: Only
Classifier: Programming Language :: Python :: 3.6
Classifier: Programming Language :: Python :: 3.7
Classifier: Topic :: Internet :: WWW/HTTP
Classifier: Topic :: Software Development :: Quality Assurance
Requires-Python: >= 3.6
Requires-Dist: mitmproxy (>=4.0.4)
Requires-Dist: HTTPolice (>=0.5.0)
